odoo/addons/intrastat_product_generic/README.rst
odoo/addons/intrastat_product_generic/__init__.py
odoo/addons/intrastat_product_generic/__manifest__.py
odoo/addons/intrastat_product_generic/i18n/intrastat_product_generic.pot
odoo/addons/intrastat_product_generic/security/intrastat_security.xml
odoo/addons/intrastat_product_generic/static/description/icon.png
odoo/addons/intrastat_product_generic/views/intrastat_product.xml
odoo11_addon_intrastat_product_generic-11.0.1.0.0.dist-info/METADATA
odoo11_addon_intrastat_product_generic-11.0.1.0.0.dist-info/RECORD
odoo11_addon_intrastat_product_generic-11.0.1.0.0.dist-info/WHEEL
odoo11_addon_intrastat_product_generic-11.0.1.0.0.dist-info/top_level.txt
